mailmerge.py
docx_mailmerge-0.5.0.dist-info/LICENSE.txt
docx_mailmerge-0.5.0.dist-info/METADATA
docx_mailmerge-0.5.0.dist-info/SOURCES 2.txt
docx_mailmerge-0.5.0.dist-info/SOURCES 3.txt
docx_mailmerge-0.5.0.dist-info/SOURCES 4.txt
docx_mailmerge-0.5.0.dist-info/SOURCES 5.txt
docx_mailmerge-0.5.0.dist-info/WHEEL
docx_mailmerge-0.5.0.dist-info/pbr.json
docx_mailmerge-0.5.0.dist-info/top_level.txt
docx_mailmerge-0.5.0.dist-info/RECORD
