Metadata-Version: 1.1
Name: docx-mailmerge
Version: 0.5.0
Summary: Performs a Mail Merge on docx (Microsoft Office Word) files
Home-page: http://github.com/Bouke/docx-mailmerge
Author: Bouke Haarsma
Author-email: bouke@webatoom.nl
License: MIT
Platform: UNKNOWN
Classifier: License :: OSI Approved :: MIT License
Classifier: Programming Language :: Python :: 2.7
Classifier: Programming Language :: Python :: 3.2
Classifier: Programming Language :: Python :: 3.3
Classifier: Programming Language :: Python :: 3.4
Classifier: Topic :: Text Processing
